Workbook

Sheet Dashboard
A1: COCA-COLA | 2021 SALES DASHBOARD
A3: Key American Coca-Cola Retailers · revenue, profit, month, brand, region and retailer comparisons
A5: TOTAL REVENUE | D5: UNITS SOLD | G5: HIGHEST SALES MONTH | J5: TOP REVENUE BRAND | M5: METRIC | N5: VALUE
A6: =SUM('Brand Performance'!B6:B11) -> 8684027.5 | D6: =SUM('Brand Performance'!D6:D11) -> 17148250 | G6: =INDEX('Monthly Sales'!A6:A17,MATCH(MAX('Monthly Sales'!B6:B17),'Monthly Sales'!B6:B17,0)) -> 2021-12 | J6: ='Brand Performance'!A6 -> Coca-Cola | M6: Revenue | N6: =A6 -> 8684027.5
M7: Profit | N7: =A11 -> 3173631.9
M8: Units | N8: =D6 -> 17148250
M9: Transactions | N9: ='Data Quality'!B7 -> 3888
A10: TOTAL OPERATING PROFIT | D10: WEIGHTED OPERATING MARGIN | G10: LOWEST MONTH REVENUE | J10: TOP RETAILER | M10: Brands | N10: ='Data Quality'!B9 -> 6
A11: =SUM('Brand Performance'!C6:C11) -> 3173631.9 | D11: =IFERROR(A11/A6,0) -> 0.36545622 | G11: =MIN('Monthly Sales'!B6:B17) -> 483530 | J11: ='Retailer Performance'!A6 -> Sodapop | M11: Regions | N11: ='Data Quality'!B10 -> 5
M12: Retailers | N12: ='Data Quality'!B11 -> 4
M13: Margin | N13: =D11 -> 0.36545622
M15: BEST / WORST MONTH | N15: SALES ($)
A16: ANALYSIS AT A GLANCE · Charts below use the same measured data as the detailed analysis tabs. | M16: 2021-12 | N16: 1045775
M17: 2021-03 | N17: 483530
M19: LEADING SEGMENT | N19: REVENUE ($)
M20: Coca-Cola | N20: 2015890
M21: West | N21: 2835100
M22: Sodapop | N22: 4403630
A74: Method: revenue and operating profit are summed; operating margin is total profit ÷ total sales. Comparisons describe 2021 only; they do not establish why sales changed.

Sheet Analysis Guide
A1: ANALYSIS PLAN & VISUALISATION MAP
A5: Question | B5: Grouping / axes | C5: Measure | D5: Technique | E5: Chart | F5: Purpose / next step
A6: Highest / lowest month | B6: Invoice date → month | C6: SUM(Total Sales) | D6: Rank months | E6: Monthly line chart | F6: Plan demand and inventory
A7: Regional variation | B7: Region | C7: Revenue, profit, margin | D7: Rank regions | E7: Regional bar chart | F7: Prioritise high-opportunity markets
A8: Brand differences | B8: Beverage Brand | C8: Revenue, units, profit | D8: Rank brands | E8: Brand bar charts | F8: Optimise product mix
A9: Brand by month | B9: Month × Brand | C9: Revenue | D9: Cross-tab comparison | E9: Multi-line chart | F9: Identify specific growth periods
A10: Brand by region | B10: Region × Brand | C10: Revenue | D10: Cross-tab comparison | E10: Grouped columns / heatmap table | F10: Tailor local assortment
A11: Retailer differences | B11: Retailer | C11: Revenue, margin | D11: Rank retailers | E11: Horizontal bar chart | F11: Target retail partnerships
A12: Most profitable product | B12: Beverage Brand | C12: Operating Profit | D12: Rank brands | E12: Profit by brand | F12: Allocate spend on contribution
A13: Pricing vs units | B13: Brand / transaction | C13: Price, units sold | D13: Association only | E13: Price table / comparisons | F13: Investigate price and volume sensitivity
A14: Geographic opportunities | B14: State / City | C14: Revenue, profit | D14: Top/bottom lists | E14: State-city tables | F14: Identify expansion candidates
A15: Operating margin | B15: Brand, retailer, region | C15: Profit / sales | D15: Weighted margin | E15: Margin bars and tables | F15: Review profitability drivers
A16: Action recommendations | B16: All comparisons | C16: Differences & tradeoffs | D16: Business interpretation | E16: Insights & Actions | F16: Propose testable next steps
... A22: Evidence boundary | B22: Descriptive comparison | C22: Not causal inference | D22: Single-year dataset | E22: Use profit and margin together | F22: Validate recommendations with experiments

Sheet Monthly Sales
A1: MONTHLY SALES | 2021
A3: Identify seasonality, sales peaks and troughs, and operating-profit trends
A5: Month | B5: Total Sales ($) | C5: Operating Profit ($) | D5: Units Sold | E5: Transactions | F5: Margin % | G5: Sales Share %
A6: 2021-01 | B6: 510750 | C6: 183334.38 | D6: 1347750 | E6: 324 | F6: =IFERROR(C6/B6,0) -> 0.3589513 | G6: =IFERROR(B6/SUM($B$6:$B$17),0) -> 0.058814876
A7: 2021-02 | B7: 484975 | C7: 174250 | D7: 1274250 | E7: 324 | F7: =IFERROR(C7/B7,0) -> 0.35929687 | G7: =IFERROR(B7/SUM($B$6:$B$17),0) -> 0.055846783
A8: 2021-03 | B8: 483530 | C8: 174392 | D8: 1204250 | E8: 324 | F8: =IFERROR(C8/B8,0) -> 0.36066428 | G8: =IFERROR(B8/SUM($B$6:$B$17),0) -> 0.055680386
A9: 2021-04 | B9: 494887.5 | C9: 177385 | D9: 1175750 | E9: 324 | F9: =IFERROR(C9/B9,0) -> 0.358435 | G9: =IFERROR(B9/SUM($B$6:$B$17),0) -> 0.056988247
A10: 2021-05 | B10: 673572.5 | C10: 248324.62 | D10: 1355000 | E10: 324 | F10: =IFERROR(C10/B10,0) -> 0.368668 | G10: =IFERROR(B10/SUM($B$6:$B$17),0) -> 0.077564529
A11: 2021-06 | B11: 903837.5 | C11: 332843.75 | D11: 1624750 | E11: 324 | F11: =IFERROR(C11/B11,0) -> 0.36825619 | G11: =IFERROR(B11/SUM($B$6:$B$17),0) -> 0.10408045
A12: 2021-07 | B12: 1041437.5 | C12: 384724.38 | D12: 1762500 | E12: 324 | F12: =IFERROR(C12/B12,0) -> 0.36941667 | G12: =IFERROR(B12/SUM($B$6:$B$17),0) -> 0.11992563
A13: 2021-08 | B13: 945275 | C13: 349565.62 | D13: 1654000 | E13: 324 | F13: =IFERROR(C13/B13,0) -> 0.3698031 | G13: =IFERROR(B13/SUM($B$6:$B$17),0) -> 0.10885214
A14: 2021-09 | B14: 681000 | C14: 248413.75 | D14: 1377250 | E14: 324 | F14: =IFERROR(C14/B14,0) -> 0.3647779 | G14: =IFERROR(B14/SUM($B$6:$B$17),0) -> 0.078419835
A15: 2021-10 | B15: 623375 | C15: 226435 | D15: 1253250 | E15: 324 | F15: =IFERROR(C15/B15,0) -> 0.36324043 | G15: =IFERROR(B15/SUM($B$6:$B$17),0) -> 0.071784089
A16: 2021-11 | B16: 795612.5 | C16: 290547.75 | D16: 1442500 | E16: 324 | F16: =IFERROR(C16/B16,0) -> 0.36518751 | G16: =IFERROR(B16/SUM($B$6:$B$17),0) -> 0.091617916
A17: 2021-12 | B17: 1045775 | C17: 383415.62 | D17: 1677000 | E17: 324 | F17: =IFERROR(C17/B17,0) -> 0.366633 | G17: =IFERROR(B17/SUM($B$6:$B$17),0) -> 0.12042511

Sheet Regional Sales
A1: REGIONAL PERFORMANCE
A3: Compare five regions by revenue, profit and operating efficiency
A5: Region | B5: Total Sales ($) | C5: Operating Profit ($) | D5: Units Sold | E5: Transactions | F5: Margin % | G5: Sales Share %
A6: West | B6: 2835100 | C6: 923014.38 | D6: 4601500 | E6: 936 | F6: =IFERROR(C6/B6,0) -> 0.32556678 | G6: =IFERROR(B6/SUM($B$6:$B$10),0) -> 0.32647294
A7: Northeast | B7: 1788347.5 | C7: 629546 | D7: 3394550 | E7: 936 | F7: =IFERROR(C7/B7,0) -> 0.35202666 | G7: =IFERROR(B7/SUM($B$6:$B$10),0) -> 0.20593526
A8: Southeast | B8: 1618935 | C8: 641553.88 | D8: 3304450 | E8: 504 | F8: =IFERROR(C8/B8,0) -> 0.39628143 | G8: =IFERROR(B8/SUM($B$6:$B$10),0) -> 0.18642675
A9: South | B9: 1291535 | C9: 542046.12 | D9: 3064800 | E9: 576 | F9: =IFERROR(C9/B9,0) -> 0.41969139 | G9: =IFERROR(B9/SUM($B$6:$B$10),0) -> 0.14872535
A10: Midwest | B10: 1150110 | C10: 437471.5 | D10: 2782950 | E10: 936 | F10: =IFERROR(C10/B10,0) -> 0.38037362 | G10: =IFERROR(B10/SUM($B$6:$B$10),0) -> 0.1324397

Sheet Brand Performance
A1: BRAND PERFORMANCE
A3: Revenue, units, profitability and weighted operating margin by beverage
A5: Beverage Brand | B5: Total Sales ($) | C5: Operating Profit ($) | D5: Units Sold | E5: Transactions | F5: Margin % | G5: Sales Share % | H5: Average Unit Price
A6: Coca-Cola | B6: 2015890 | C6: 793197.25 | D6: 4133250 | E6: 648 | F6: =IFERROR(C6/B6,0) -> 0.39347249 | G6: =IFERROR(B6/SUM($B$6:$B$11),0) -> 0.23213768 | H6: =IFERROR(B6/D6,0) -> 0.48772516
A7: Dasani Water | B7: 1725837.5 | C7: 655700 | D7: 3000250 | E7: 648 | F7: =IFERROR(C7/B7,0) -> 0.37993148 | G7: =IFERROR(B7/SUM($B$6:$B$11),0) -> 0.19873699 | H7: =IFERROR(B7/D7,0) -> 0.57523123
A8: Diet Coke | B8: 1481425 | C8: 494317.5 | D8: 3001500 | E8: 648 | F8: =IFERROR(C8/B8,0) -> 0.33367703 | G8: =IFERROR(B8/SUM($B$6:$B$11),0) -> 0.17059193 | H8: =IFERROR(B8/D8,0) -> 0.49356155
A9: Sprite | B9: 1235587.5 | C9: 430519.62 | D9: 2701250 | E9: 648 | F9: =IFERROR(C9/B9,0) -> 0.34843313 | G9: =IFERROR(B9/SUM($B$6:$B$11),0) -> 0.14228277 | H9: =IFERROR(B9/D9,0) -> 0.45741323
A10: Powerade | B10: 1193637.5 | C10: 427071.88 | D10: 2120750 | E10: 648 | F10: =IFERROR(C10/B10,0) -> 0.35779026 | G10: =IFERROR(B10/SUM($B$6:$B$11),0) -> 0.13745206 | H10: =IFERROR(B10/D10,0) -> 0.56283744
A11: Fanta | B11: 1031650 | C11: 372825.62 | D11: 2191250 | E11: 648 | F11: =IFERROR(C11/B11,0) -> 0.3613877 | G11: =IFERROR(B11/SUM($B$6:$B$11),0) -> 0.11879856 | H11: =IFERROR(B11/D11,0) -> 0.47080434

Sheet Retailer Performance
A1: RETAILER PERFORMANCE
A3: Which retail partner generates the most sales and profit?
A5: Retailer | B5: Total Sales ($) | C5: Operating Profit ($) | D5: Units Sold | E5: Transactions | F5: Margin % | G5: Sales Share %
A6: Sodapop | B6: 4403630 | C6: 1647936.4 | D6: 9153950 | E6: 2304 | F6: =IFERROR(C6/B6,0) -> 0.37422226 | G6: =IFERROR(B6/SUM($B$6:$B$9),0) -> 0.50709535
A7: FizzySip | B7: 2584450 | C7: 835759.38 | D7: 4109000 | E7: 864 | F7: =IFERROR(C7/B7,0) -> 0.32337997 | G7: =IFERROR(B7/SUM($B$6:$B$9),0) -> 0.29760961
A8: BevCo | B8: 1291535 | C8: 542046.12 | D8: 3064800 | E8: 576 | F8: =IFERROR(C8/B8,0) -> 0.41969139 | G8: =IFERROR(B8/SUM($B$6:$B$9),0) -> 0.14872535
A9: DreamCo | B9: 404412.5 | C9: 147890 | D9: 820500 | E9: 144 | F9: =IFERROR(C9/B9,0) -> 0.36569097 | G9: =IFERROR(B9/SUM($B$6:$B$9),0) -> 0.046569694

Sheet Brand Monthly
A1: BRAND × MONTH | REVENUE
A3: Monthly trend for each of six brands; all figures are sales revenue in USD
A5: Period / Region | B5: Coca-Cola | C5: Dasani Water | D5: Diet Coke | E5: Sprite | F5: Powerade | G5: Fanta | H5: All Brands
A6: 2021-01 | B6: 110012.5 | C6: 93662.5 | D6: 94112.5 | E6: 76912.5 | F6: 77350 | G6: 58700 | H6: 510750
A7: 2021-02 | B7: 121250 | C7: 84950 | D7: 80150 | E7: 71612.5 | F7: 73137.5 | G7: 53875 | H7: 484975
A8: 2021-03 | B8: 123667.5 | C8: 82525 | D8: 85575 | E8: 73625 | F8: 63075 | G8: 55062.5 | H8: 483530
A9: 2021-04 | B9: 128250 | C9: 99987.5 | D9: 79112.5 | E9: 69350 | F9: 64225 | G9: 53962.5 | H9: 494887.5
A10: 2021-05 | B10: 166372.5 | C10: 150300 | D10: 103350 | E10: 92300 | F10: 85087.5 | G10: 76162.5 | H10: 673572.5
A11: 2021-06 | B11: 193825 | C11: 213387.5 | D11: 140500 | E11: 128650 | F11: 116975 | G11: 110500 | H11: 903837.5
A12: 2021-07 | B12: 237587.5 | C12: 212825 | D12: 174187.5 | E12: 150250 | F12: 146750 | G12: 119837.5 | H12: 1041437.5
A13: 2021-08 | B13: 232600 | C13: 161062.5 | D13: 179900 | E13: 144750 | F13: 119500 | G13: 107462.5 | H13: 945275
A14: 2021-09 | B14: 170737.5 | C14: 119562.5 | D14: 131187.5 | E14: 91350 | F14: 91400 | G14: 76762.5 | H14: 681000
A15: 2021-10 | B15: 146575 | C15: 125087.5 | D15: 113700 | E15: 82150 | F15: 83025 | G15: 72837.5 | H15: 623375
A16: 2021-11 | B16: 150787.5 | C16: 181900 | D16: 118612.5 | E16: 105337.5 | F16: 127850 | G16: 111125 | H16: 795612.5
A17: 2021-12 | B17: 234225 | C17: 200587.5 | D17: 181037.5 | E17: 149300 | F17: 145262.5 | G17: 135362.5 | H17: 1045775
A18: TOTAL | B18: 2015890 | C18: 1725837.5 | D18: 1481425 | E18: 1235587.5 | F18: 1193637.5 | G18: 1031650 | H18: 8684027.5

Sheet Brand Regional
A1: BRAND × REGION | REVENUE
A3: Geographic mix of six brands across five regions; values are USD
A5: Period / Region | B5: Coca-Cola | C5: Dasani Water | D5: Diet Coke | E5: Sprite | F5: Powerade | G5: Fanta | H5: All Brands
A6: West | B6: 549700 | C6: 537562.5 | D6: 541150 | E6: 461875 | F6: 369762.5 | G6: 375050 | H6: 2835100
A7: Northeast | B7: 498157.5 | C7: 357712.5 | D7: 277050 | E7: 223690 | F7: 242875 | G7: 188862.5 | H7: 1788347.5
A8: Southeast | B8: 375482.5 | C8: 319662.5 | D8: 253100 | E8: 209165 | F8: 262775 | G8: 198750 | H8: 1618935
A9: South | B9: 248022.5 | C9: 267837.5 | D9: 231450 | E9: 207425 | F9: 171050 | G9: 165750 | H9: 1291535
A10: Midwest | B10: 344527.5 | C10: 243062.5 | D10: 178675 | E10: 133432.5 | F10: 147175 | G10: 103237.5 | H10: 1150110
A11: TOTAL | B11: 2015890 | C11: 1725837.5 | D11: 1481425 | E11: 1235587.5 | F11: 1193637.5 | G11: 1031650 | H11: 8684027.5

Sheet Geography
A1: GEOGRAPHIC SALES
A3: State and city ranking by revenue, plus profit and weighted margin
A5: Region | B5: State | C5: Sales ($) | D5: Profit ($) | E5: Units | F5: Operating Margin | H5: State | I5: City | J5: Sales ($) | K5: Profit ($) | L5: Units | M5: Operating Margin
A6: Northeast | B6: New York | C6: 582675 | D6: 203082.5 | E6: 1125200 | F6: =IFERROR(D6/C6,0) -> 0.34853477 | H6: New York | I6: New York | J6: 391767.5 | K6: 135983.5 | L6: 706600 | M6: =IFERROR(K6/J6,0) -> 0.34710255
A7: West | B7: California | C7: 582400 | D7: 183895.62 | E7: 1037250 | F7: =IFERROR(D7/C7,0) -> 0.31575485 | H7: California | I7: San Francisco | J7: 331750 | K7: 96640.625 | L7: 544750 | M7: =IFERROR(K7/J7,0) -> 0.29130558
A8: Southeast | B8: Florida | C8: 561850 | D8: 214731.25 | E8: 1051700 | F8: =IFERROR(D8/C8,0) -> 0.38218608 | H8: Florida | I8: Miami | J8: 319025 | K8: 121600.62 | L8: 597850 | M8: =IFERROR(K8/J8,0) -> 0.38116331
A9: South | B9: Texas | C9: 440987.5 | D9: 176324.38 | E9: 1014250 | F9: =IFERROR(D9/C9,0) -> 0.39983985 | H9: Georgia | I9: Atlanta | J9: 292210 | K9: 111621.5 | L9: 579350 | M9: =IFERROR(K9/J9,0) -> 0.38199069
A10: Southeast | B10: Georgia | C10: 292210 | D10: 111621.5 | E10: 579350 | F10: =IFERROR(D10/C10,0) -> 0.38199069 | H10: Hawaii | I10: Honolulu | J10: 255425 | K10: 77950.625 | L10: 353500 | M10: =IFERROR(K10/J10,0) -> 0.30518009
A11: West | B11: Hawaii | C11: 255425 | D11: 77950.625 | E11: 353500 | F11: =IFERROR(D11/C11,0) -> 0.30518009 | H11: California | I11: Los Angeles | J11: 250650 | K11: 87255 | L11: 492500 | M11: =IFERROR(K11/J11,0) -> 0.3481149
A12: West | B12: Washington | C12: 250237.5 | D12: 64440.625 | E12: 348750 | F12: =IFERROR(D12/C12,0) -> 0.25751786 | H12: Washington | I12: Seattle | J12: 250237.5 | K12: 64440.625 | L12: 348750 | M12: =IFERROR(K12/J12,0) -> 0.25751786
A13: Southeast | B13: South Carolina | C13: 238055 | D13: 96130.125 | E13: 507350 | F13: =IFERROR(D13/C13,0) -> 0.40381477 | H13: Florida | I13: Orlando | J13: 242825 | K13: 93130.625 | L13: 453850 | M13: =IFERROR(K13/J13,0) -> 0.38352981
A14: West | B14: Oregon | C14: 226300 | D14: 89835 | E14: 346750 | F14: =IFERROR(D14/C14,0) -> 0.39697304 | H14: Texas | I14: Houston | J14: 238850 | K14: 92478.125 | L14: 566000 | M14: =IFERROR(K14/J14,0) -> 0.38718076
A15: West | B15: Alaska | C15: 213437.5 | D15: 54539.375 | E15: 312250 | F15: =IFERROR(D15/C15,0) -> 0.25552855 | H15: South Carolina | I15: Charleston | J15: 238055 | K15: 96130.125 | L15: 507350 | M15: =IFERROR(K15/J15,0) -> 0.40381477
A16: West | B16: Colorado | C16: 202725 | D16: 74185.625 | E16: 324250 | F16: =IFERROR(D16/C16,0) -> 0.36594216 | H16: Oregon | I16: Portland | J16: 226300 | K16: 89835 | L16: 346750 | M16: =IFERROR(K16/J16,0) -> 0.39697304
A17: West | B17: Wyoming | C17: 199937.5 | D17: 69359.375 | E17: 310750 | F17: =IFERROR(D17/C17,0) -> 0.34690528 | H17: Alaska | I17: Anchorage | J17: 213437.5 | K17: 54539.375 | L17: 312250 | M17: =IFERROR(K17/J17,0) -> 0.25552855
... A55: Midwest | B55: Nebraska | C55: 54380 | D55: 21991.5 | E55: 136350 | F55: =IFERROR(D55/C55,0) -> 0.40440419 | H55: Iowa | I55: Des Moines | J55: 72667.5 | K55: 25784.625 | L55: 183100 | M55: =IFERROR(K55/J55,0) -> 0.35483022
H56: North Dakota | I56: Fargo | J56: 72380 | K56: 25662.125 | L56: 184100 | M56: =IFERROR(K56/J56,0) -> 0.35454718
H57: West Virginia | I57: Charleston | J57: 71145 | K57: 25036.125 | L57: 154600 | M57: =IFERROR(K57/J57,0) -> 0.3519028
H58: Minnesota | I58: Minneapolis | J58: 67910 | K58: 23980.75 | L58: 156850 | M58: =IFERROR(K58/J58,0) -> 0.35312546
H59: Nebraska | I59: Omaha | J59: 54380 | K59: 21991.5 | L59: 136350 | M59: =IFERROR(K59/J59,0) -> 0.40440419

Sheet Price and Margin
A1: PRICE & OPERATING MARGIN
A5: Brand | B5: Revenue ($) | C5: Units Sold | D5: Price / Unit ($) | E5: Profit ($) | F5: Margin % | G5: Transactions | H5: Profit / Unit ($)
A6: Coca-Cola | B6: 2015890 | C6: 4133250 | D6: =IFERROR(B6/C6,0) -> 0.48772516 | E6: 793197.25 | F6: =IFERROR(E6/B6,0) -> 0.39347249 | G6: 648 | H6: =IFERROR(E6/C6,0) -> 0.19190643
A7: Dasani Water | B7: 1725837.5 | C7: 3000250 | D7: =IFERROR(B7/C7,0) -> 0.57523123 | E7: 655700 | F7: =IFERROR(E7/B7,0) -> 0.37993148 | G7: 648 | H7: =IFERROR(E7/C7,0) -> 0.21854845
A8: Diet Coke | B8: 1481425 | C8: 3001500 | D8: =IFERROR(B8/C8,0) -> 0.49356155 | E8: 494317.5 | F8: =IFERROR(E8/B8,0) -> 0.33367703 | G8: 648 | H8: =IFERROR(E8/C8,0) -> 0.16469015
A9: Sprite | B9: 1235587.5 | C9: 2701250 | D9: =IFERROR(B9/C9,0) -> 0.45741323 | E9: 430519.62 | F9: =IFERROR(E9/B9,0) -> 0.34843313 | G9: 648 | H9: =IFERROR(E9/C9,0) -> 0.15937793
A10: Powerade | B10: 1193637.5 | C10: 2120750 | D10: =IFERROR(B10/C10,0) -> 0.56283744 | E10: 427071.88 | F10: =IFERROR(E10/B10,0) -> 0.35779026 | G10: 648 | H10: =IFERROR(E10/C10,0) -> 0.20137776
A11: Fanta | B11: 1031650 | C11: 2191250 | D11: =IFERROR(B11/C11,0) -> 0.47080434 | E11: 372825.62 | F11: =IFERROR(E11/B11,0) -> 0.3613877 | G11: 648 | H11: =IFERROR(E11/C11,0) -> 0.1701429

Sheet Insights and Actions
A1: KEY INSIGHTS → RECOMMENDED ACTIONS
A5: Theme | B5: Data-supported finding | C5: Business action | D5: Follow-up to validate
A6: Month peak | B6: 2021-12: $1,045,775; lowest 2021-03: $483,530. | C6: Review capacity and inventory ahead of strong months. | D6: Compare 2022+ months and promotional calendars; test seasonality.
A7: Regions | B7: West leads with $2,835,100; Midwest is lowest at $1,150,110. | C7: Tailor regional inventory and distribution decisions. | D7: Compare store footprint, population, and sell-through before investing.
A8: Brand sales | B8: Coca-Cola is the top revenue brand ($2,015,890); Fanta is lowest ($1,031,650). | C8: Protect shelf availability of strong lines; pilot weaker-brand promotion. | D8: Test awareness, availability, pricing and retailer coverage.
A9: Brand profit | B9: Coca-Cola has highest operating profit ($793,197). | C9: Prioritise gross contribution, not just unit volume. | D9: Review advertising cost and incremental profit after promotions.
A10: Brand margin | B10: Coca-Cola leads on weighted margin (39.3%). | C10: Review high-margin lines as possible mix opportunities. | D10: Compare distribution costs and demand before scaling.
A11: Retailers | B11: Sodapop generates $4,403,630 (50.7% of total sales). | C11: Review channel concentration and service levels. | D11: Normalise sales by store count, size and contract terms.
A12: Brand-month pattern | B12: Brand Monthly tab displays all 72 month-brand observations. | C12: Schedule brand-specific demand reviews before seasonal peaks. | D12: Repeat across years; isolate promotions and stockouts.
A13: Brand-region mix | B13: Brand Regional tab compares all six brands in five regions. | C13: Consider region-specific assortment tests. | D13: Evaluate margin, distribution availability and competitor mix.
A14: Price-volume caution | B14: Average realised price differs by brand; units also vary. | C14: Avoid assuming higher prices cause lower sales. | D14: Estimate price response with controlled tests or panel data.
A15: Profit efficiency | B15: Total weighted operating margin is 36.5%. | C15: Use both operating profit and margin in scorecards. | D15: Review cost-to-serve and retailer-level cost allocations.

Sheet Data Quality
A1: DATA VALIDATION & LIMITATIONS
A5: Check | B5: Result | C5: Meaning
A6: Original transaction rows | B6: 3888 | C6: Rows from source B6:M3893
A7: Valid sales records | B7: 3888 | C7: Records with a retailer and numeric Total Sales
A8: Excluded / invalid records | B8: 0 | C8: Excluded before aggregation
A9: Distinct beverage brands | B9: 6 | C9: Products in the data
A10: Distinct regions | B10: 5 | C10: Region values as supplied
A11: Distinct retailers | B11: 4 | C11: Retailer names as supplied
A12: Distinct states | B12: 50 | C12: United States states represented
A13: Distinct cities (state + city) | B13: 54 | C13: Distinct geographic city keys
A14: Missing cells in required 12 fields | B14: 0 | C14: Source field completeness
A15: Sales vs units × price discrepancies | B15: 0 | C15: Tolerance $0.01
A16: Margin vs profit / sales discrepancies | B16: 0 | C16: Tolerance 0.1 percentage points
A17: Date coverage | B17: 02 Jan 2021 to 25 Dec 2021 | C17: The analysis is for 2021 only
A20: Interpretation note | B20: Detail
A21: Operating margin | B21: Profit / Sales, not simple average of record margins
A22: Price vs quantity | B22: Cross-sectional pattern; cannot demonstrate causal price elasticity
A23: Time horizon | B23: A single year does not prove a recurring seasonal pattern
A24: Revenue differences | B24: Do not establish the reason without cost, marketing or availability data

Sheet Clean Data
A1: TRANSACTION DATA | 2021
A5: Retailer | B5: Retailer ID | C5: Invoice Date | D5: Region | E5: State | F5: City | G5: Beverage Brand | H5: Price per Unit | I5: Units Sold | J5: Total Sales | K5: Operating Profit | L5: Operating Margin | M5: Month | N5: Quarter
A6: Sodapop | B6: 1185732 | C6: 44210 | D6: Northeast | E6: New York | F6: New York | G6: Coca-Cola | H6: 0.5 | I6: 12000 | J6: 6000 | K6: 3000 | L6: 0.5 | M6: 2021-01 | N6: Q1
A7: Sodapop | B7: 1185732 | C7: 44210 | D7: Northeast | E7: New York | F7: New York | G7: Diet Coke | H7: 0.5 | I7: 10000 | J7: 5000 | K7: 1500 | L7: 0.3 | M7: 2021-01 | N7: Q1
A8: Sodapop | B8: 1185732 | C8: 44210 | D8: Northeast | E8: New York | F8: New York | G8: Sprite | H8: 0.4 | I8: 10000 | J8: 4000 | K8: 1400 | L8: 0.35 | M8: 2021-01 | N8: Q1
A9: Sodapop | B9: 1185732 | C9: 44210 | D9: Northeast | E9: New York | F9: New York | G9: Fanta | H9: 0.45 | I9: 8500 | J9: 3825 | K9: 1338.75 | L9: 0.35 | M9: 2021-01 | N9: Q1
A10: Sodapop | B10: 1185732 | C10: 44210 | D10: Northeast | E10: New York | F10: New York | G10: Powerade | H10: 0.6 | I10: 9000 | J10: 5400 | K10: 1620 | L10: 0.3 | M10: 2021-01 | N10: Q1
A11: Sodapop | B11: 1185732 | C11: 44210 | D11: Northeast | E11: New York | F11: New York | G11: Dasani Water | H11: 0.5 | I11: 10000 | J11: 5000 | K11: 1250 | L11: 0.25 | M11: 2021-01 | N11: Q1
A12: Sodapop | B12: 1185732 | C12: 44239 | D12: Northeast | E12: New York | F12: New York | G12: Coca-Cola | H12: 0.5 | I12: 12500 | J12: 6250 | K12: 3125 | L12: 0.5 | M12: 2021-02 | N12: Q1
A13: Sodapop | B13: 1185732 | C13: 44239 | D13: Northeast | E13: New York | F13: New York | G13: Diet Coke | H13: 0.5 | I13: 9000 | J13: 4500 | K13: 1350 | L13: 0.3 | M13: 2021-02 | N13: Q1
A14: Sodapop | B14: 1185732 | C14: 44239 | D14: Northeast | E14: New York | F14: New York | G14: Sprite | H14: 0.4 | I14: 9500 | J14: 3800 | K14: 1330 | L14: 0.35 | M14: 2021-02 | N14: Q1
A15: Sodapop | B15: 1185732 | C15: 44239 | D15: Northeast | E15: New York | F15: New York | G15: Fanta | H15: 0.45 | I15: 8250 | J15: 3712.5 | K15: 1299.375 | L15: 0.35 | M15: 2021-02 | N15: Q1
A16: Sodapop | B16: 1185732 | C16: 44239 | D16: Northeast | E16: New York | F16: New York | G16: Powerade | H16: 0.6 | I16: 9000 | J16: 5400 | K16: 1620 | L16: 0.3 | M16: 2021-02 | N16: Q1
A17: Sodapop | B17: 1185732 | C17: 44239 | D17: Northeast | E17: New York | F17: New York | G17: Dasani Water | H17: 0.5 | I17: 10000 | J17: 5000 | K17: 1250 | L17: 0.25 | M17: 2021-02 | N17: Q1
... A3893: Sodapop | B3893: 1185732 | C3893: 44550 | D3893: Northeast | E3893: New Hampshire | F3893: Manchester | G3893: Dasani Water | H3893: 0.8 | I3893: 4250 | J3893: 3400 | K3893: 1020 | L3893: 0.3 | M3893: 2021-12 | N3893: Q4
